weapp_cli/__init__.py
weapp_cli/cli.py
weapp_cli/sample.py
weapp_cli/wegene_utils.py
weapp_cli/file_templates/html_template.html
weapp_cli/file_templates/main.R
weapp_cli/file_templates/main.py
weapp_cli/file_templates/pacman.R
weapp_cli/file_templates/requirements.txt
weapp_cli/file_templates/wegene_utils.R
weapp_cli/file_templates/wegene_utils.py
weapp_cli/file_templates/python27/main.py
weapp_cli/file_templates/python27/requirements.txt
weapp_cli/file_templates/python27/wegene_utils.py
weapp_cli/file_templates/python3/main.py
weapp_cli/file_templates/python3/requirements.txt
weapp_cli/file_templates/python3/wegene_utils.py
weapp_cli/file_templates/r/main.R
weapp_cli/file_templates/r/pacman.R
weapp_cli/file_templates/r/wegene_utils.R
weapp_cli/indexes/index_wegene_affy_2.idx
wegene_weapp_cli-1.1.1.dist-info/METADATA
wegene_weapp_cli-1.1.1.dist-info/WHEEL
wegene_weapp_cli-1.1.1.dist-info/entry_points.txt
wegene_weapp_cli-1.1.1.dist-info/top_level.txt
wegene_weapp_cli-1.1.1.dist-info/RECORD
