Metadata-Version: 2.1
Name: wegene-weapp-cli
Version: 1.1.1
Summary: A CLI tool for generating, testing and packaging weapps
Home-page: https://github.com/wegene-llc/wegene-weapp-cli
Author: Xiaoli Wu
Author-email: wxl@wegene.com
License: MIT
Platform: any
Classifier: Development Status :: 5 - Production/Stable
Classifier: Environment :: Console
Classifier: Intended Audience :: Developers
Classifier: License :: OSI Approved :: MIT License
Classifier: Operating System :: POSIX
Classifier: Operating System :: MacOS
Classifier: Operating System :: Unix
Classifier: Operating System :: Microsoft :: Windows
Classifier: Programming Language :: Python
Classifier: Programming Language :: Python :: 3
Classifier: Topic :: Software Development :: Libraries :: Python Modules
Requires-Dist: click
Requires-Dist: wget
Requires-Dist: markdown
